<?xml version='1.0'  encoding='UTF-8' ?>
<history>
	<historyItem>
		<sql><![CDATA[SELECT employee_id, last_name, department_id, salary,
    DECODE(department_id, 20, salary*0.2,
                            30, salary*03,
                            40, salary*0.4,
                            0) bonus
FROM employees;]]></sql>
		<connection><![CDATA[hr]]></connection>
		<timestamp><![CDATA[1669189782431]]></timestamp>
		<type><![CDATA[SQL]]></type>
		<executed><![CDATA[1]]></executed>
		<execTime><![CDATA[0.004]]></execTime>
	</historyItem>
</history>
